{
  "exercises": [
    {
      "id": 1,
      "title": "Exercise 1",
      "subtitle": "Subtitle 1",
      "publish_date": "2023-04-21T19:36:56.529477Z",
      "deadline": "2099-12-10T12:00:00Z",
      "limit_of_attempts": 3,
      "visibility": false,
      "students_class": {
        "id": 1,
        "name": "Class 1",
        "num_students": 2,
        "image": "/media/image.png"
      },
      "num_answers": 0
    },
    {
      "id": 2,
      "title": "Exercise 2",
      "subtitle": "Subtitle 2",
      "publish_date": "2023-04-21T19:36:57.182535Z",
      "deadline": "2098-12-10T12:00:00Z",
      "limit_of_attempts": 3,
      "visibility": true,
      "students_class": {
        "id": 1,
        "name": "Class 1",
        "num_students": 2,
        "image": "/media/image.png"
      },
      "num_answers": 0
    },
    {
      "id": 3,
      "title": "Exercise 3",
      "subtitle": "Subtitle 3",
      "publish_date": "2023-04-21T19:36:57.839656Z",
      "deadline": "1994-12-10T12:00:00Z",
      "limit_of_attempts": 3,
      "visibility": true,
      "students_class": {
        "id": 1,
        "name": "Class 1",
        "num_students": 2,
        "image": "/media/image.png"
      },
      "num_answers": 0
    }
  ],
  "classes": [
    {
      "id": 1,
      "name": "Class 1"
    },
    {
      "id": 2,
      "name": "ML-3"
    }
  ]
}